thclient/__init__.py
thclient/client.py
thclient/perfherder.py
treeherder_client-4.0.0.dist-info/DESCRIPTION.rst
treeherder_client-4.0.0.dist-info/METADATA
treeherder_client-4.0.0.dist-info/RECORD
treeherder_client-4.0.0.dist-info/WHEEL
treeherder_client-4.0.0.dist-info/metadata.json
treeherder_client-4.0.0.dist-info/top_level.txt
