Metadata-Version: 1.1
Name: treeherder-client
Version: 4.0.0
Summary: Python library to retrieve and submit data to the Treeherder API
Home-page: https://github.com/mozilla/treeherder
Author: Mozilla Automation and Testing Team
Author-email: tools@lists.mozilla.org
License: MPL
Platform: UNKNOWN
Classifier: Environment :: Console
Classifier: Intended Audience :: Developers
Classifier: License :: OSI Approved :: Mozilla Public License 2.0 (MPL 2.0)
Classifier: Natural Language :: English
Classifier: Operating System :: OS Independent
Classifier: Programming Language :: Python
Classifier: Topic :: Software Development :: Libraries :: Python Modules
